{"allhistory_participants": 271, "bmitickets": 81.54, "bmitickets_30": 93, "bmitickets_365": 87, "bmitickets_7": 125, "changed": 5229, "changed_30": 257, "changed_365": 1084, "changed_7": 73, "changers": 157, "changers_30": 31, "changers_365": 81, "changers_7": 14, "closed": 4276, "closed_30": 86, "closed_365": 652, "closed_7": 30, "closers": 55, "closers_30": 7, "closers_365": 23, "closers_7": 4, "diff_netbmitickets_30": -24, "diff_netbmitickets_365": 6, "diff_netbmitickets_7": 67, "diff_netchanged_30": 79, "diff_netchanged_365": 12, "diff_netchanged_7": 20, "diff_netchangers_30": 3, "diff_netchangers_365": 23, "diff_netchangers_7": 3, "diff_netclosed_30": -3, "diff_netclosed_365": 139, "diff_netclosed_7": 10, "diff_netclosers_30": -2, "diff_netclosers_365": 3, "diff_netclosers_7": 0, "diff_netopened_30": 16, "diff_netopened_365": 114, "diff_netopened_7": -10, "diff_netopeners_30": 2, "diff_netopeners_365": 15, "diff_netopeners_7": 4, "domains": 1, "first_date": "2010-05-20", "last_date": "2015-08-21", "opened": 5244, "opened_30": 92, "opened_365": 744, "opened_7": 24, "openers": 168, "openers_30": 28, "openers_365": 78, "openers_7": 15, "organizations": 0, "percentage_bmitickets_30": 20, "percentage_bmitickets_365": 7, "percentage_bmitickets_7": 115, "percentage_changed_30": 44, "percentage_changed_365": 1, "percentage_changed_7": 37, "percentage_changers_30": 10, "percentage_changers_365": 39, "percentage_changers_7": 27, "percentage_closed_30": 3, "percentage_closed_365": 27, "percentage_closed_7": 50, "percentage_closers_30": 22, "percentage_closers_365": 15, "percentage_closers_7": 0, "percentage_opened_30": 21, "percentage_opened_365": 18, "percentage_opened_7": 29, "percentage_openers_30": 7, "percentage_openers_365": 23, "percentage_openers_7": 36, "trackers": 1, "type": "trac", "url": "https://fedorahosted.org/freeipa"}