{"diff_netrepositories_30": -1, "diff_netrepositories_365": 0, "diff_netrepositories_7": 0, "diff_netsenders_30": 7, "diff_netsenders_365": 18, "diff_netsenders_7": 2, "diff_netsenders_init_30": 4, "diff_netsenders_init_365": 9, "diff_netsenders_init_7": 0, "diff_netsenders_response_30": 8, "diff_netsenders_response_365": 18, "diff_netsenders_response_7": 2, "diff_netsent_30": -69, "diff_netsent_365": 1928, "diff_netsent_7": 61, "diff_netsent_response_30": -61, "diff_netsent_response_365": 1857, "diff_netsent_response_7": 63, "diff_netthreads_30": -8, "diff_netthreads_365": 71, "diff_netthreads_7": -2, "first_date": "2007-06-29", "last_date": "2015-08-18", "percentage_repositories_30": 33, "percentage_repositories_365": 0, "percentage_repositories_7": 0, "percentage_senders_30": 20, "percentage_senders_365": 32, "percentage_senders_7": 7, "percentage_senders_init_30": 18, "percentage_senders_init_365": 25, "percentage_senders_init_7": 0, "percentage_senders_response_30": 24, "percentage_senders_response_365": 36, "percentage_senders_response_7": 8, "percentage_sent_30": 8, "percentage_sent_365": 27, "percentage_sent_7": 37, "percentage_sent_response_30": 8, "percentage_sent_response_365": 30, "percentage_sent_response_7": 47, "percentage_threads_30": 6, "percentage_threads_365": 8, "percentage_threads_7": 6, "repositories": 3, "repositories_30": 2, "repositories_365": 3, "repositories_7": 2, "senders": 158, "senders_30": 41, "senders_365": 73, "senders_7": 28, "senders_init": 104, "senders_init_30": 26, "senders_init_365": 44, "senders_init_7": 13, "senders_response": 147, "senders_response_30": 41, "senders_response_365": 68, "senders_response_7": 27, "sent": 43216, "sent_30": 785, "sent_365": 8917, "sent_7": 224, "sent_response": 35788, "sent_response_30": 666, "sent_response_365": 7967, "sent_response_7": 197, "threads": 7428, "threads_30": 119, "threads_365": 950, "threads_7": 27}