{"diff_netrepositories_30": 0, "diff_netrepositories_365": 0, "diff_netrepositories_7": -1, "diff_netsenders_30": 1, "diff_netsenders_365": 21, "diff_netsenders_7": 5, "diff_netsenders_init_30": 2, "diff_netsenders_init_365": 10, "diff_netsenders_init_7": 7, "diff_netsenders_response_30": 3, "diff_netsenders_response_365": 20, "diff_netsenders_response_7": 4, "diff_netsent_30": 76, "diff_netsent_365": 437, "diff_netsent_7": 134, "diff_netsent_response_30": 34, "diff_netsent_response_365": 488, "diff_netsent_response_7": 116, "diff_netthreads_30": 42, "diff_netthreads_365": -51, "diff_netthreads_7": 18, "first_date": "2007-06-29", "last_date": "2015-11-26", "percentage_repositories_30": 0, "percentage_repositories_365": 0, "percentage_repositories_7": 33, "percentage_senders_30": 2, "percentage_senders_365": 37, "percentage_senders_7": 22, "percentage_senders_init_30": 10, "percentage_senders_init_365": 28, "percentage_senders_init_7": 87, "percentage_senders_response_30": 9, "percentage_senders_response_365": 38, "percentage_senders_response_7": 18, "percentage_sent_30": 11, "percentage_sent_365": 5, "percentage_sent_7": 115, "percentage_sent_response_30": 5, "percentage_sent_response_365": 6, "percentage_sent_response_7": 123, "percentage_threads_30": 65, "percentage_threads_365": 5, "percentage_threads_7": 81, "repositories": 3, "repositories_30": 3, "repositories_365": 3, "repositories_7": 2, "senders": 165, "senders_30": 35, "senders_365": 77, "senders_7": 27, "senders_init": 109, "senders_init_30": 21, "senders_init_365": 45, "senders_init_7": 15, "senders_response": 154, "senders_response_30": 35, "senders_response_365": 72, "senders_response_7": 26, "sent": 45478, "sent_30": 724, "sent_365": 8521, "sent_7": 250, "sent_response": 37782, "sent_response_30": 618, "sent_response_365": 7608, "sent_response_7": 210, "threads": 7696, "threads_30": 106, "threads_365": 913, "threads_7": 40}