{"diff_netrepositories_30": 0, "diff_netrepositories_365": 0, "diff_netrepositories_7": 0, "diff_netsenders_30": -5, "diff_netsenders_365": 20, "diff_netsenders_7": -8, "diff_netsenders_init_30": -5, "diff_netsenders_init_365": 7, "diff_netsenders_init_7": -6, "diff_netsenders_response_30": -6, "diff_netsenders_response_365": 20, "diff_netsenders_response_7": -8, "diff_netsent_30": -45, "diff_netsent_365": 1725, "diff_netsent_7": -75, "diff_netsent_response_30": -9, "diff_netsent_response_365": 1678, "diff_netsent_response_7": -64, "diff_netthreads_30": -36, "diff_netthreads_365": 47, "diff_netthreads_7": -11, "first_date": "2007-06-29", "last_date": "2015-09-13", "percentage_repositories_30": 0, "percentage_repositories_365": 0, "percentage_repositories_7": 0, "percentage_senders_30": 12, "percentage_senders_365": 38, "percentage_senders_7": 29, "percentage_senders_init_30": 19, "percentage_senders_init_365": 20, "percentage_senders_init_7": 54, "percentage_senders_response_30": 14, "percentage_senders_response_365": 41, "percentage_senders_response_7": 29, "percentage_sent_30": 6, "percentage_sent_365": 24, "percentage_sent_7": 43, "percentage_sent_response_30": 1, "percentage_sent_response_365": 26, "percentage_sent_response_7": 41, "percentage_threads_30": 31, "percentage_threads_365": 5, "percentage_threads_7": 55, "repositories": 3, "repositories_30": 2, "repositories_365": 3, "repositories_7": 2, "senders": 151, "senders_30": 36, "senders_365": 72, "senders_7": 19, "senders_init": 97, "senders_init_30": 21, "senders_init_365": 42, "senders_init_7": 5, "senders_response": 143, "senders_response_30": 35, "senders_response_365": 68, "senders_response_7": 19, "sent": 43716, "sent_30": 699, "sent_365": 8866, "sent_7": 99, "sent_response": 36273, "sent_response_30": 622, "sent_response_365": 7926, "sent_response_7": 90, "threads": 7443, "threads_30": 77, "threads_365": 940, "threads_7": 9}