{"diff_netrepositories_30": 0, "diff_netrepositories_365": 0, "diff_netrepositories_7": 1, "diff_netsenders_30": 3, "diff_netsenders_365": 18, "diff_netsenders_7": 0, "diff_netsenders_init_30": 8, "diff_netsenders_init_365": 6, "diff_netsenders_init_7": 3, "diff_netsenders_response_30": 3, "diff_netsenders_response_365": 18, "diff_netsenders_response_7": -1, "diff_netsent_30": 128, "diff_netsent_365": 881, "diff_netsent_7": -19, "diff_netsent_response_30": 88, "diff_netsent_response_365": 903, "diff_netsent_response_7": -24, "diff_netthreads_30": 40, "diff_netthreads_365": -22, "diff_netthreads_7": 5, "first_date": "2007-06-29", "last_date": "2015-11-04", "percentage_repositories_30": 0, "percentage_repositories_365": 0, "percentage_repositories_7": 50, "percentage_senders_30": 10, "percentage_senders_365": 33, "percentage_senders_7": 0, "percentage_senders_init_30": 57, "percentage_senders_init_365": 17, "percentage_senders_init_7": 33, "percentage_senders_response_30": 10, "percentage_senders_response_365": 36, "percentage_senders_response_7": 5, "percentage_sent_30": 25, "percentage_sent_365": 11, "percentage_sent_7": 12, "percentage_sent_response_30": 18, "percentage_sent_response_365": 13, "percentage_sent_response_7": 17, "percentage_threads_30": 105, "percentage_threads_365": 2, "percentage_threads_7": 31, "repositories": 3, "repositories_30": 3, "repositories_365": 3, "repositories_7": 3, "senders": 2, "senders_30": 33, "senders_365": 71, "senders_7": 20, "senders_init": 2, "senders_init_30": 22, "senders_init_365": 41, "senders_init_7": 12, "senders_response": 2, "senders_response_30": 32, "senders_response_365": 67, "senders_response_7": 18, "sent": 7590, "sent_30": 640, "sent_365": 8579, "sent_7": 138, "sent_response": 6045, "sent_response_30": 562, "sent_response_365": 7680, "sent_response_7": 117, "threads": 1545, "threads_30": 78, "threads_365": 899, "threads_7": 21}