{"actions": [36442, 254, 220, 31, 31, 2, 3, 2, 2, 1], "added_lines": [1950451.0, 1063.0, 8031.0, 1190.0, 1190.0, 2.0, 59.0, 228.0, 12.0, 6.0], "added_lines_30": [8680.0, 16.0, 0, 0, 0, 0, 0, 0, 0, 0], "added_lines_365": [117389.0, 687.0, 0, 40.0, 40.0, 0, 0, 0, 0, 0], "added_lines_7": [504.0, 2.0, 0, 0, 0, 0, 0, 0, 0, 0], "authors": [71, 7, 2, 1, 1, 1, 1, 1, 1, 1], "authors_30": [16, 2, 0, 0, 0, 0, 0, 0, 0, 0], "authors_365": [37, 2, 0, 1, 1, 0, 0, 0, 0, 0], "authors_7": [7, 1, 0, 0, 0, 0, 0, 0, 0, 0], "avg_commits_author": [163.61, 11.71, 31.0, 12.0, 12.0, 2.0, 2.0, 2.0, 2.0, 1.0], "avg_commits_month": [115.01, 1.49, 1.63, 0.35, 0.35, null, null, null, null, null], "avg_files_author": [76.08, 30.29, 75.5, 25.0, 25.0, 2.0, 2.0, 2.0, 2.0, 1.0], "avg_files_month": [53.49, 3.85, 3.97, 0.74, 0.74, null, null, null, null, null], "branches": [14, 9, 5, 2, 2, 2, 1, 2, 2, 1], "commits": [11616, 82, 62, 12, 12, 2, 2, 2, 2, 1], "commits_30": [136, 3, 0, 0, 0, 0, 0, 0, 0, 0], "commits_365": [1476, 45, 0, 9, 9, 0, 0, 0, 0, 0], "commits_7": [18, 1, 0, 0, 0, 0, 0, 0, 0, 0], "committers": [21, 0, 0, 0, 0, 0, 1, 0, 0, 0], "diff_netadded_lines_30": [-1388.0, -71.0, 0, 0, 0, 0, 0, 0, 0, 0], "diff_netadded_lines_365": [-46311.0, 468.0, 0, 40.0, 40.0, 0, 0, -228.0, 0, 0], "diff_netadded_lines_7": [-3668.0, 2.0, 0, 0, 0, 0, 0, 0, 0, 0], "diff_netauthors_30": [0, 1, 0, 0, 0, 0, 0, 0, 0, 0], "diff_netauthors_365": [13, 0, 0, 1, 1, 0, 0, -1, 0, 0], "diff_netauthors_7": [-1, 1, 0, 0, 0, 0, 0, 0, 0, 0], "diff_netcommits_30": [35, -6, 0, 0, 0, 0, 0, 0, 0, 0], "diff_netcommits_365": [-322, 20, 0, 9, 9, 0, 0, -2, 0, 0], "diff_netcommits_7": [-4, 1, 0, 0, 0, 0, 0, 0, 0, 0], "diff_netfiles_30": [-7, -8, 0, 0, 0, 0, 0, 0, 0, 0], "diff_netfiles_365": [-398, 66, 0, 12, 12, 0, 0, -2, 0, 0], "diff_netfiles_7": [-25, 2, 0, 0, 0, 0, 0, 0, 0, 0], "diff_netnewauthors_30": [1, 0, 0, 0, 0, 0, 0, 0, 0, 0], "diff_netnewauthors_365": [10, -2, 0, 0, 0, 0, 0, -1, 0, 0], "diff_netnewauthors_7": [0, 0, 0, 0, 0, 0, 0, 0, 0, 0], "diff_netremoved_lines_30": [3295.0, -5.0, 0, 0, 0, 0, 0, 0, 0, 0], "diff_netremoved_lines_365": [-18482.0, 49.0, 0, 21.0, 21.0, 0, 0, -28.0, 0, 0], "diff_netremoved_lines_7": [-3172.0, 2.0, 0, 0, 0, 0, 0, 0, 0, 0], "files": [5402, 212, 151, 25, 25, 2, 2, 2, 2, 1], "files_30": [162, 4, 0, 0, 0, 0, 0, 0, 0, 0], "files_365": [1067, 98, 0, 12, 12, 0, 0, 0, 0, 0], "files_7": [17, 2, 0, 0, 0, 0, 0, 0, 0, 0], "first_date": ["2007-06-28", "2011-05-04", "2010-09-27", "2012-12-05", "2012-12-05", "2012-11-28", "2007-10-02", "2014-03-07", "2011-12-21", "2011-12-03"], "last_date": ["2015-12-08", "2015-12-06", "2013-11-27", "2015-10-06", "2015-10-06", "2012-11-28", "2007-10-03", "2014-03-07", "2011-12-21", "2011-12-03"], "name": ["Red Hat", "Independent", "Citrix", "Canonical, Ltd.", "Debian GNU/Linux", "GoodData", "Johns Hopkins University", "Other Media", "Radicore AB", "ALT Linux, Ltd."], "newauthors": [71, 7, 2, 1, 1, 1, 1, 1, 1, 1], "newauthors_30": [1, 0, 0, 0, 0, 0, 0, 0, 0, 0], "newauthors_365": [17, 0, 0, 0, 0, 0, 0, 0, 0, 0], "newauthors_7": [0, 0, 0, 0, 0, 0, 0, 0, 0, 0], "percentage_added_lines_30": [13, 81, 0, 0, 0, 0, 0, 0, 0, 0], "percentage_added_lines_365": [28, 213, 0, 0, 0, 0, 0, 100, 0, 0], "percentage_added_lines_7": [87, 0, 0, 0, 0, 0, 0, 0, 0, 0], "percentage_authors_30": [0, 100, 0, 0, 0, 0, 0, 0, 0, 0], "percentage_authors_365": [54, 0, 0, 0, 0, 0, 0, 100, 0, 0], "percentage_authors_7": [12, 0, 0, 0, 0, 0, 0, 0, 0, 0], "percentage_commits_30": [34, 66, 0, 0, 0, 0, 0, 0, 0, 0], "percentage_commits_365": [17, 80, 0, 0, 0, 0, 0, 100, 0, 0], "percentage_commits_7": [18, 0, 0, 0, 0, 0, 0, 0, 0, 0], "percentage_files_30": [4, 66, 0, 0, 0, 0, 0, 0, 0, 0], "percentage_files_365": [27, 206, 0, 0, 0, 0, 0, 100, 0, 0], "percentage_files_7": [59, 0, 0, 0, 0, 0, 0, 0, 0, 0], "percentage_newauthors_30": [0, 0, 0, 0, 0, 0, 0, 0, 0, 0], "percentage_newauthors_365": [142, 100, 0, 0, 0, 0, 0, 100, 0, 0], "percentage_newauthors_7": [0, 0, 0, 0, 0, 0, 0, 0, 0, 0], "percentage_removed_lines_30": [138, 55, 0, 0, 0, 0, 0, 0, 0, 0], "percentage_removed_lines_365": [26, 21, 0, 0, 0, 0, 0, 100, 0, 0], "percentage_removed_lines_7": [98, 0, 0, 0, 0, 0, 0, 0, 0, 0], "removed_lines": [1305352.0, 663.0, 990.0, 1068.0, 1068.0, 2.0, 3.0, 28.0, 4.0, 0.0], "removed_lines_30": [5678.0, 4.0, 0, 0, 0, 0, 0, 0, 0, 0], "removed_lines_365": [51457.0, 279.0, 0, 21.0, 21.0, 0, 0, 0, 0, 0], "removed_lines_7": [48.0, 2.0, 0, 0, 0, 0, 0, 0, 0, 0], "repositories": [1, 1, 1, 1, 1, 1, 1, 1, 1, 1]}